molcrafts_molq-0.1.0.dist-info/licenses/LICENSE
molq/__init__.py
molq/base.py
molq/resources.py
molq/submit.py
molq/cli/__init__.py
molq/cli/main.py
molq/submitor/__init__.py
molq/submitor/base.py
molq/submitor/local.py
molq/submitor/slurm.py
molcrafts_molq-0.1.0.dist-info/METADATA
molcrafts_molq-0.1.0.dist-info/WHEEL
molcrafts_molq-0.1.0.dist-info/entry_points.txt
molcrafts_molq-0.1.0.dist-info/top_level.txt
molcrafts_molq-0.1.0.dist-info/RECORD
